doless/Doless.py
doless/__init__.py
DoLess-0.1.1.dist-info/METADATA
DoLess-0.1.1.dist-info/WHEEL
DoLess-0.1.1.dist-info/top_level.txt
DoLess-0.1.1.dist-info/RECORD
