Metadata-Version: 2.1
Name: DoLess
Version: 0.1.1
Summary: DoLess is a Python library that provides a set of functions that can be used to perform various tasks in Python. The library is designed to be easy to use and provides a simple functions and class where you can use in your Python scripts to perform basic tasks in just calling functions and methods.
Author: raunak_sh
Classifier: Programming Language :: Python :: 3
Classifier: License :: OSI Approved :: MIT License
Classifier: Operating System :: OS Independent
Requires-Dist: requests
